pyuuid7-0.1.0.dist-info/METADATA
pyuuid7-0.1.0.dist-info/WHEEL
pyuuid7-0.1.0.dist-info/licenses/LICENSE
pyuuid7/__init__.py
pyuuid7/pyuuid7.cpython-312-x86_64-linux-gnu.so
pyuuid7-0.1.0.dist-info/RECORD
