Metadata-Version: 2.4
Name: pyuuid7
Version: 0.1.0
Classifier: Development Status :: 4 - Beta
Classifier: Intended Audience :: Developers
Classifier: License :: OSI Approved :: MIT License
Classifier: Programming Language :: Rust
Classifier: Programming Language :: Python :: 3
Classifier: Programming Language :: Python :: 3.9
Classifier: Programming Language :: Python :: 3.10
Classifier: Programming Language :: Python :: 3.11
Classifier: Programming Language :: Python :: 3.12
Classifier: Programming Language :: Python :: Implementation :: CPython
Classifier: Topic :: Software Development :: Libraries
License-File: LICENSE
Summary: Fast UUID v4, v5, v7 generation in Rust
Keywords: uuid,uuid7,uuid5,uuid4,rust
License: MIT
Requires-Python: >=3.9
Project-URL: Repository, https://github.com/tarcisio/pyuuid7
